{
  "id": "e2e2701b-7a88-4c4c-839b-3c5f9ac998c2",
  "prevId": "00000000-0000-0000-0000-000000000000",
  "version": "7",
  "dialect": "postgresql",
  "tables": {
    "public.amz_credits_ledger": {
      "name": "amz_credits_ledger",
      "schema": "",
      "columns": {
        "id": {
          "name": "id",
          "type": "serial",
          "primaryKey": true,
          "notNull": true
        },
        "user_id": {
          "name": "user_id",
          "type": "integer",
          "primaryKey": false,
          "notNull": true
        },
        "amount": {
          "name": "amount",
          "type": "integer",
          "primaryKey": false,
          "notNull": true
        },
        "remaining_amount": {
          "name": "remaining_amount",
          "type": "integer",
          "primaryKey": false,
          "notNull": true
        },
        "type": {
          "name": "type",
          "type": "text",
          "primaryKey": false,
          "notNull": true
        },
        "description": {
          "name": "description",
          "type": "text",
          "primaryKey": false,
          "notNull": false
        },
        "expires_at": {
          "name": "expires_at",
          "type": "timestamp",
          "primaryKey": false,
          "notNull": false
        },
        "created_at": {
          "name": "created_at",
          "type": "timestamp",
          "primaryKey": false,
          "notNull": false,
          "default": "now()"
        }
      },
      "indexes": {},
      "foreignKeys": {
        "amz_credits_ledger_user_id_amz_users_id_fk": {
          "name": "amz_credits_ledger_user_id_amz_users_id_fk",
          "tableFrom": "amz_credits_ledger",
          "tableTo": "amz_users",
          "columnsFrom": [
            "user_id"
          ],
          "columnsTo": [
            "id"
          ],
          "onDelete": "no action",
          "onUpdate": "no action"
        }
      },
      "compositePrimaryKeys": {},
      "uniqueConstraints": {},
      "policies": {},
      "checkConstraints": {},
      "isRLSEnabled": false
    },
    "public.amz_generations": {
      "name": "amz_generations",
      "schema": "",
      "columns": {
        "id": {
          "name": "id",
          "type": "serial",
          "primaryKey": true,
          "notNull": true
        },
        "user_id": {
          "name": "user_id",
          "type": "integer",
          "primaryKey": false,
          "notNull": true
        },
        "type": {
          "name": "type",
          "type": "text",
          "primaryKey": false,
          "notNull": true
        },
        "cost_credits": {
          "name": "cost_credits",
          "type": "integer",
          "primaryKey": false,
          "notNull": true,
          "default": 1
        },
        "created_at": {
          "name": "created_at",
          "type": "timestamp",
          "primaryKey": false,
          "notNull": false,
          "default": "now()"
        }
      },
      "indexes": {},
      "foreignKeys": {
        "amz_generations_user_id_amz_users_id_fk": {
          "name": "amz_generations_user_id_amz_users_id_fk",
          "tableFrom": "amz_generations",
          "tableTo": "amz_users",
          "columnsFrom": [
            "user_id"
          ],
          "columnsTo": [
            "id"
          ],
          "onDelete": "no action",
          "onUpdate": "no action"
        }
      },
      "compositePrimaryKeys": {},
      "uniqueConstraints": {},
      "policies": {},
      "checkConstraints": {},
      "isRLSEnabled": false
    },
    "public.amz_listings": {
      "name": "amz_listings",
      "schema": "",
      "columns": {
        "id": {
          "name": "id",
          "type": "serial",
          "primaryKey": true,
          "notNull": true
        },
        "user_id": {
          "name": "user_id",
          "type": "integer",
          "primaryKey": false,
          "notNull": true
        },
        "product_name": {
          "name": "product_name",
          "type": "text",
          "primaryKey": false,
          "notNull": true
        },
        "listing_data": {
          "name": "listing_data",
          "type": "jsonb",
          "primaryKey": false,
          "notNull": true
        },
        "generated_images": {
          "name": "generated_images",
          "type": "text[]",
          "primaryKey": false,
          "notNull": false
        },
        "created_at": {
          "name": "created_at",
          "type": "timestamp",
          "primaryKey": false,
          "notNull": false,
          "default": "now()"
        }
      },
      "indexes": {},
      "foreignKeys": {
        "amz_listings_user_id_amz_users_id_fk": {
          "name": "amz_listings_user_id_amz_users_id_fk",
          "tableFrom": "amz_listings",
          "tableTo": "amz_users",
          "columnsFrom": [
            "user_id"
          ],
          "columnsTo": [
            "id"
          ],
          "onDelete": "no action",
          "onUpdate": "no action"
        }
      },
      "compositePrimaryKeys": {},
      "uniqueConstraints": {},
      "policies": {},
      "checkConstraints": {},
      "isRLSEnabled": false
    },
    "public.amz_plans": {
      "name": "amz_plans",
      "schema": "",
      "columns": {
        "id": {
          "name": "id",
          "type": "serial",
          "primaryKey": true,
          "notNull": true
        },
        "name": {
          "name": "name",
          "type": "text",
          "primaryKey": false,
          "notNull": true
        },
        "monthly_price_eur": {
          "name": "monthly_price_eur",
          "type": "integer",
          "primaryKey": false,
          "notNull": true
        },
        "credit_limit": {
          "name": "credit_limit",
          "type": "integer",
          "primaryKey": false,
          "notNull": true
        },
        "features_json": {
          "name": "features_json",
          "type": "jsonb",
          "primaryKey": false,
          "notNull": true
        },
        "created_at": {
          "name": "created_at",
          "type": "timestamp",
          "primaryKey": false,
          "notNull": false,
          "default": "now()"
        }
      },
      "indexes": {},
      "foreignKeys": {},
      "compositePrimaryKeys": {},
      "uniqueConstraints": {
        "amz_plans_name_unique": {
          "name": "amz_plans_name_unique",
          "nullsNotDistinct": false,
          "columns": [
            "name"
          ]
        }
      },
      "policies": {},
      "checkConstraints": {},
      "isRLSEnabled": false
    },
    "public.amz_subscriptions": {
      "name": "amz_subscriptions",
      "schema": "",
      "columns": {
        "id": {
          "name": "id",
          "type": "serial",
          "primaryKey": true,
          "notNull": true
        },
        "user_id": {
          "name": "user_id",
          "type": "integer",
          "primaryKey": false,
          "notNull": true
        },
        "stripe_subscription_id": {
          "name": "stripe_subscription_id",
          "type": "text",
          "primaryKey": false,
          "notNull": true
        },
        "status": {
          "name": "status",
          "type": "text",
          "primaryKey": false,
          "notNull": true
        },
        "plan_type": {
          "name": "plan_type",
          "type": "text",
          "primaryKey": false,
          "notNull": true,
          "default": "'FREE'"
        },
        "current_period_end": {
          "name": "current_period_end",
          "type": "timestamp",
          "primaryKey": false,
          "notNull": false
        },
        "created_at": {
          "name": "created_at",
          "type": "timestamp",
          "primaryKey": false,
          "notNull": false,
          "default": "now()"
        }
      },
      "indexes": {},
      "foreignKeys": {
        "amz_subscriptions_user_id_amz_users_id_fk": {
          "name": "amz_subscriptions_user_id_amz_users_id_fk",
          "tableFrom": "amz_subscriptions",
          "tableTo": "amz_users",
          "columnsFrom": [
            "user_id"
          ],
          "columnsTo": [
            "id"
          ],
          "onDelete": "no action",
          "onUpdate": "no action"
        }
      },
      "compositePrimaryKeys": {},
      "uniqueConstraints": {
        "amz_subscriptions_stripe_subscription_id_unique": {
          "name": "amz_subscriptions_stripe_subscription_id_unique",
          "nullsNotDistinct": false,
          "columns": [
            "stripe_subscription_id"
          ]
        }
      },
      "policies": {},
      "checkConstraints": {},
      "isRLSEnabled": false
    },
    "public.amz_system_config": {
      "name": "amz_system_config",
      "schema": "",
      "columns": {
        "key": {
          "name": "key",
          "type": "text",
          "primaryKey": true,
          "notNull": true
        },
        "value": {
          "name": "value",
          "type": "text",
          "primaryKey": false,
          "notNull": true
        },
        "description": {
          "name": "description",
          "type": "text",
          "primaryKey": false,
          "notNull": false
        },
        "updated_at": {
          "name": "updated_at",
          "type": "timestamp",
          "primaryKey": false,
          "notNull": false,
          "default": "now()"
        }
      },
      "indexes": {},
      "foreignKeys": {},
      "compositePrimaryKeys": {},
      "uniqueConstraints": {},
      "policies": {},
      "checkConstraints": {},
      "isRLSEnabled": false
    },
    "public.amz_usage_history": {
      "name": "amz_usage_history",
      "schema": "",
      "columns": {
        "id": {
          "name": "id",
          "type": "serial",
          "primaryKey": true,
          "notNull": true
        },
        "user_id": {
          "name": "user_id",
          "type": "integer",
          "primaryKey": false,
          "notNull": true
        },
        "feature_used": {
          "name": "feature_used",
          "type": "text",
          "primaryKey": false,
          "notNull": true
        },
        "credits_spent": {
          "name": "credits_spent",
          "type": "integer",
          "primaryKey": false,
          "notNull": true
        },
        "metadata": {
          "name": "metadata",
          "type": "jsonb",
          "primaryKey": false,
          "notNull": false
        },
        "created_at": {
          "name": "created_at",
          "type": "timestamp",
          "primaryKey": false,
          "notNull": false,
          "default": "now()"
        }
      },
      "indexes": {},
      "foreignKeys": {
        "amz_usage_history_user_id_amz_users_id_fk": {
          "name": "amz_usage_history_user_id_amz_users_id_fk",
          "tableFrom": "amz_usage_history",
          "tableTo": "amz_users",
          "columnsFrom": [
            "user_id"
          ],
          "columnsTo": [
            "id"
          ],
          "onDelete": "no action",
          "onUpdate": "no action"
        }
      },
      "compositePrimaryKeys": {},
      "uniqueConstraints": {},
      "policies": {},
      "checkConstraints": {},
      "isRLSEnabled": false
    },
    "public.amz_user_subscriptions": {
      "name": "amz_user_subscriptions",
      "schema": "",
      "columns": {
        "id": {
          "name": "id",
          "type": "serial",
          "primaryKey": true,
          "notNull": true
        },
        "user_id": {
          "name": "user_id",
          "type": "integer",
          "primaryKey": false,
          "notNull": true
        },
        "plan_id": {
          "name": "plan_id",
          "type": "integer",
          "primaryKey": false,
          "notNull": true
        },
        "stripe_subscription_id": {
          "name": "stripe_subscription_id",
          "type": "text",
          "primaryKey": false,
          "notNull": false
        },
        "status": {
          "name": "status",
          "type": "text",
          "primaryKey": false,
          "notNull": true
        },
        "current_period_end": {
          "name": "current_period_end",
          "type": "timestamp",
          "primaryKey": false,
          "notNull": false
        },
        "created_at": {
          "name": "created_at",
          "type": "timestamp",
          "primaryKey": false,
          "notNull": false,
          "default": "now()"
        },
        "updated_at": {
          "name": "updated_at",
          "type": "timestamp",
          "primaryKey": false,
          "notNull": false,
          "default": "now()"
        }
      },
      "indexes": {},
      "foreignKeys": {
        "amz_user_subscriptions_user_id_amz_users_id_fk": {
          "name": "amz_user_subscriptions_user_id_amz_users_id_fk",
          "tableFrom": "amz_user_subscriptions",
          "tableTo": "amz_users",
          "columnsFrom": [
            "user_id"
          ],
          "columnsTo": [
            "id"
          ],
          "onDelete": "no action",
          "onUpdate": "no action"
        },
        "amz_user_subscriptions_plan_id_amz_plans_id_fk": {
          "name": "amz_user_subscriptions_plan_id_amz_plans_id_fk",
          "tableFrom": "amz_user_subscriptions",
          "tableTo": "amz_plans",
          "columnsFrom": [
            "plan_id"
          ],
          "columnsTo": [
            "id"
          ],
          "onDelete": "no action",
          "onUpdate": "no action"
        }
      },
      "compositePrimaryKeys": {},
      "uniqueConstraints": {
        "amz_user_subscriptions_stripe_subscription_id_unique": {
          "name": "amz_user_subscriptions_stripe_subscription_id_unique",
          "nullsNotDistinct": false,
          "columns": [
            "stripe_subscription_id"
          ]
        }
      },
      "policies": {},
      "checkConstraints": {},
      "isRLSEnabled": false
    },
    "public.amz_users": {
      "name": "amz_users",
      "schema": "",
      "columns": {
        "id": {
          "name": "id",
          "type": "serial",
          "primaryKey": true,
          "notNull": true
        },
        "email": {
          "name": "email",
          "type": "text",
          "primaryKey": false,
          "notNull": true
        },
        "password_hash": {
          "name": "password_hash",
          "type": "text",
          "primaryKey": false,
          "notNull": true
        },
        "role": {
          "name": "role",
          "type": "text",
          "primaryKey": false,
          "notNull": true,
          "default": "'USER'"
        },
        "credits_balance": {
          "name": "credits_balance",
          "type": "integer",
          "primaryKey": false,
          "notNull": true,
          "default": 5
        },
        "stripe_customer_id": {
          "name": "stripe_customer_id",
          "type": "text",
          "primaryKey": false,
          "notNull": false
        },
        "phone": {
          "name": "phone",
          "type": "text",
          "primaryKey": false,
          "notNull": false
        },
        "company_name": {
          "name": "company_name",
          "type": "text",
          "primaryKey": false,
          "notNull": false
        },
        "address_street": {
          "name": "address_street",
          "type": "text",
          "primaryKey": false,
          "notNull": false
        },
        "address_city": {
          "name": "address_city",
          "type": "text",
          "primaryKey": false,
          "notNull": false
        },
        "address_state": {
          "name": "address_state",
          "type": "text",
          "primaryKey": false,
          "notNull": false
        },
        "address_zip": {
          "name": "address_zip",
          "type": "text",
          "primaryKey": false,
          "notNull": false
        },
        "created_at": {
          "name": "created_at",
          "type": "timestamp",
          "primaryKey": false,
          "notNull": false,
          "default": "now()"
        },
        "banned_at": {
          "name": "banned_at",
          "type": "timestamp",
          "primaryKey": false,
          "notNull": false
        },
        "activated_at": {
          "name": "activated_at",
          "type": "timestamp",
          "primaryKey": false,
          "notNull": false
        },
        "activation_token": {
          "name": "activation_token",
          "type": "text",
          "primaryKey": false,
          "notNull": false
        },
        "reset_password_token": {
          "name": "reset_password_token",
          "type": "text",
          "primaryKey": false,
          "notNull": false
        },
        "reset_password_expires": {
          "name": "reset_password_expires",
          "type": "timestamp",
          "primaryKey": false,
          "notNull": false
        }
      },
      "indexes": {},
      "foreignKeys": {},
      "compositePrimaryKeys": {},
      "uniqueConstraints": {
        "amz_users_email_unique": {
          "name": "amz_users_email_unique",
          "nullsNotDistinct": false,
          "columns": [
            "email"
          ]
        }
      },
      "policies": {},
      "checkConstraints": {},
      "isRLSEnabled": false
    }
  },
  "enums": {},
  "schemas": {},
  "sequences": {},
  "roles": {},
  "policies": {},
  "views": {},
  "_meta": {
    "columns": {},
    "schemas": {},
    "tables": {}
  }
}